.gitignore
LICENSE
MANIFEST
MANIFEST.in
README.rst
requirements.in
requirements.txt
setup.cfg
setup.py
test-requirements.txt
tox.ini
SilentDune_Server.egg-info/PKG-INFO
SilentDune_Server.egg-info/SOURCES.txt
SilentDune_Server.egg-info/dependency_links.txt
SilentDune_Server.egg-info/requires.txt
SilentDune_Server.egg-info/top_level.txt
install/__init__.py
silentdune_server/__init__.py
silentdune_server/manage.py
silentdune_server/notes.txt
silentdune_server/todo.py
silentdune_server/apps/__init__.py
silentdune_server/apps/models.py
silentdune_server/apps/accounts/__init__.py
silentdune_server/apps/accounts/admin.py
silentdune_server/apps/accounts/forms.py
silentdune_server/apps/accounts/models.py
silentdune_server/apps/accounts/urls.py
silentdune_server/apps/accounts/views.py
silentdune_server/apps/accounts/migrations/0001_initial.py
silentdune_server/apps/accounts/migrations/0002_userprofile.py
silentdune_server/apps/accounts/migrations/0003_userprofile_oauth_scope.py
silentdune_server/apps/accounts/migrations/0004_auto_20160108_1546.py
silentdune_server/apps/accounts/migrations/0004_auto_20160111_1810.py
silentdune_server/apps/accounts/migrations/0005_merge.py
silentdune_server/apps/accounts/migrations/0006_auto_20160119_1852.py
silentdune_server/apps/accounts/migrations/0007_auto_20160427_1709.py
silentdune_server/apps/accounts/migrations/0008_auto_20160503_1612.py
silentdune_server/apps/accounts/migrations/0009_userprofile_utc_offset.py
silentdune_server/apps/accounts/migrations/0010_auto_20160713_1617.py
silentdune_server/apps/accounts/migrations/0011_auto_20160722_1621.py
silentdune_server/apps/accounts/migrations/__init__.py
silentdune_server/apps/accounts/templates/accounts/__base.html
silentdune_server/apps/accounts/templates/accounts/create_profile.html
silentdune_server/apps/accounts/templates/accounts/edit_profile.html
silentdune_server/apps/accounts/templates/accounts/login.html
silentdune_server/apps/accounts/templates/accounts/password_change_form.html
silentdune_server/apps/accounts/templates/accounts/profile.html
silentdune_server/apps/accounts/templates/accounts/view_profile.html
silentdune_server/apps/alerts/__init__.py
