Metadata-Version: 1.1
Name: SilentDune-Server
Version: 0.6
Summary: Silent Dune Server
Home-page: https://github.com/EntPack/SilentDune
Author: Robert Abram
Author-email: robert.abram@entpack.com
License: UNKNOWN
Keywords: firewall,security
Platform: UNKNOWN
Classifier: Development Status :: 4 - Beta
Classifier: Programming Language :: Python
Classifier: Environment :: Console
Classifier: License :: OSI Approved :: GNU General Public License v3 (GPLv3)
Classifier: Operating System :: POSIX :: Linux
